nanowire_plugin/__init__.py
nanowire_plugin/group_tools/__init__.py
nanowire_plugin/single_file_tools/__init__.py
nanowire_plugin-1.0.19.data/data/VERSION
tester/__init__.py
nanowire_plugin-1.0.19.dist-info/LICENSE
nanowire_plugin-1.0.19.dist-info/METADATA
nanowire_plugin-1.0.19.dist-info/WHEEL
nanowire_plugin-1.0.19.dist-info/top_level.txt
nanowire_plugin-1.0.19.dist-info/RECORD
